{
    "id": 6,
    "titre": "Dreamara - La Planète des Rêves",
    "image": "Dreamara.jpg",
    "date_depart": "2026-02-20",
    "date_retour": "2026-02-28",
    "duree": 8,
    "specificites": "Un monde onirique où chaque zone reflète un rêve différent.",
    "prix_total": 22500,
    "etapes": [
        {
            "titre": "Vallée des Nuages Magiques",
            "date_arrivee": "2026-02-20",
            "date_depart": "2026-02-25",
            "duree": 5,
            "position": {
                "gps": "80.0000, -70.0000",
                "nom_lieu": "Île Flottante Arc-en-ciel"
            },
            "options": [
                {"type": "expérience", "nom": "Tapis Volant à travers les rêves", "prix_par_personne": 260},
                {"type": "hébergement", "nom": "Hôtel des Songes", "prix_par_personne": 280}
            ]
        }
    ],
    "activites": [
    {
        "nom": "Tapis Volant à travers les rêves",
        "description": "Parcourez un monde onirique en volant sur un tapis magique.",
        "prix": 260
    },
    {
        "nom": "Exploration des rêves partagés",
        "description": "Découvrez les pensées d'autres voyageurs en fusionnant vos rêves.",
        "prix": 280
    },
    {
        "nom": "Voyage en bateau sur une rivière étoilée",
        "description": "Naviguez sur une mer cosmique illuminée.",
        "prix": 300
    },
    {
        "nom": "Randonnée dans une forêt de bonbons",
        "description": "Goûtez aux fruits sucrés d’une jungle colorée.",
        "prix": 150
    }
]

}
